README.md
setup.cfg
setup.py
ngen/__init__.py
ngen/exceptions.py
ngen/models.py
ngen/singletons.py
ngen/tid.py
ngen/utils.py
ngen/validators.py
ngen.egg-info/PKG-INFO
ngen.egg-info/SOURCES.txt
ngen.egg-info/dependency_links.txt
ngen.egg-info/requires.txt
ngen.egg-info/top_level.txt
ngen/tests/__init__.py
ngen/tests/test_models.py
ngen/tests/test_singletons.py
ngen/tests/test_tid.py
ngen/tests/test_timers.py
ngen/tests/test_utils.py
ngen/tests/test_validators.py