Metadata-Version: 1.1
Name: ngen
Version: 1.0.1
Summary: `ngen` is a utility library housing commonly used design patterns.
Home-page: https://github.com/anthonyalmarza/ngen
Author: Anthony
Author-email: UNKNOWN
License: UNKNOWN
Keywords: singletons,parsers,transitions,timers
Platform: UNKNOWN
Classifier: Intended Audience :: Developers
Classifier: Natural Language :: English
Classifier: Operating System :: OS Independent
Classifier: Programming Language :: Python
